hybraut_executor_watchdog/__about__.py
hybraut_executor_watchdog/__init__.py
hybraut_executor_watchdog/fsm.py
hybraut_executor_watchdog/hybraut_bus/__init__.py
hybraut_executor_watchdog/hybraut_bus/event_bus.py
hybraut_executor_watchdog/hybraut_bus/ros_bus.py
hybraut_executor_watchdog/hybraut_bus/status_bus.py
hybraut_executor_watchdog/hybraut_consts/__init__.py
hybraut_executor_watchdog/hybraut_consts/event_enum.py
hybraut_executor_watchdog/hybraut_consts/status_enum.py
hybraut_executor_watchdog-0.0.1.dist-info/METADATA
hybraut_executor_watchdog-0.0.1.dist-info/WHEEL
hybraut_executor_watchdog-0.0.1.dist-info/licenses/LICENSE.txt
hybraut_executor_watchdog-0.0.1.dist-info/RECORD
